{
  "document_name": "1.pdf",
  "source_result_path": "data/output/1_result.json",
  "total_keyword_groups": 17,
  "keyword_groups": [
    {
      "representative_keyword": "Contracting Parties",
      "related_keywords": [
        "Orion Digital Solutions Pte. Ltd.",
        "Service Provider",
        "Lotus Retail Group Joint Stock Company",
        "Client"
      ],
      "provision_type": "parties",
      "metadata": {
        "page": 1,
        "id": "seg_001",
        "source": "data\\input\\1.pdf"
      },
      "evidences": [
        {
          "evidence_text": "The Service Provider is Orion Digital Solutions Pte. Ltd. The Client is Lotus Retail Group Joint Stock Company.",
          "exact_text": "The Service Provider is Orion Digital Solutions Pte. Ltd., a Singapore company. The Client is Lotus Retail Group Joint Stock Company, a Vietnamese company.",
          "page": 1,
          "id": "seg_002",
          "source": "data\\input\\1.pdf",
          "validation_status": "passed",
          "confidence": 0.99
        }
      ]
    },
    {
      "representative_keyword": "Contracting Parties",
      "related_keywords": [
        "Service Provider",
        "Orion Digital Solutions Pte. Ltd.",
        "Client",
        "Lotus Retail Group Joint Stock Company"
      ],
      "provision_type": "parties",
      "metadata": {
        "page": 1,
        "id": "seg_002",
        "source": "data\\input\\1.pdf",
        "clause_no": "1"
      },
      "evidences": [
        {
          "evidence_text": "The Service Provider is Orion Digital Solutions Pte. Ltd. The Client is Lotus Retail Group Joint Stock Company.",
          "exact_text": "The Service Provider is Orion Digital Solutions Pte. Ltd., a Singapore company. The Client is Lotus Retail Group Joint Stock Company, a Vietnamese company.",
          "page": 1,
          "id": "seg_002",
          "source": "data\\input\\1.pdf",
          "validation_status": "passed",
          "confidence": 0.99
        }
      ]
    },
    {
      "representative_keyword": "Effective Date",
      "related_keywords": [
        "Effective Date",
        "Commencement Date",
        "Start Date"
      ],
      "provision_type": "effective_date",
      "metadata": {
        "page": 1,
        "id": "seg_003",
        "source": "data\\input\\1.pdf",
        "clause_no": "2"
      },
      "evidences": [
        {
          "evidence_text": "Effective Date, Commencement Date, and Start Date are April 1, 2026.",
          "exact_text": "Effective Date: April 1, 2026. Commencement Date: April 1, 2026. Start Date: April 1, 2026.",
          "page": 1,
          "id": "seg_003",
          "source": "data\\input\\1.pdf",
          "validation_status": "passed",
          "confidence": 0.99
        }
      ]
    },
    {
      "representative_keyword": "Contract Term",
      "related_keywords": [
        "End Date",
        "Expiration Date",
        "effective"
      ],
      "provision_type": "term",
      "metadata": {
        "page": 1,
        "id": "seg_003",
        "source": "data\\input\\1.pdf",
        "clause_no": "2"
      },
      "evidences": [
        {
          "evidence_text": "This Agreement remains effective from the Effective Date until the End Date unless terminated earlier.",
          "exact_text": "This Agreement remains effective from the Effective Date until the End Date unless terminated earlier under the termination clause.",
          "page": 1,
          "id": "seg_003",
          "source": "data\\input\\1.pdf",
          "validation_status": "passed",
          "confidence": 0.98
        }
      ]
    },
    {
      "representative_keyword": "Scope of Services",
      "related_keywords": [
        "design",
        "develop",
        "maintain",
        "support",
        "retail operations platform",
        "requirements analysis",
        "software development",
        "API integration",
        "bug fixing",
        "monthly maintenance",
        "production monitoring",
        "technical support"
      ],
      "provision_type": "services",
      "metadata": {
        "page": 1,
        "id": "seg_004",
        "source": "data\\input\\1.pdf",
        "clause_no": "3"
      },
      "evidences": [
        {
          "evidence_text": "The Service Provider shall design, develop, maintain, and support a retail operations platform for the Client.",
          "exact_text": "The Service Provider shall design, develop, maintain, and support a retail operations platform for the Client.",
          "page": 1,
          "id": "seg_004",
          "source": "data\\input\\1.pdf",
          "validation_status": "passed",
          "confidence": 0.99
        }
      ]
    },
    {
      "representative_keyword": "Deliverables",
      "related_keywords": [
        "source code",
        "deployment scripts",
        "user documentation",
        "monthly maintenance reports",
        "review",
        "deliverable",
        "accepted"
      ],
      "provision_type": "delivery",
      "metadata": {
        "page": 1,
        "id": "seg_005",
        "source": "data\\input\\1.pdf",
        "clause_no": "4"
      },
      "evidences": [
        {
          "evidence_text": "The Service Provider shall deliver source code, deployment scripts, user documentation, and monthly maintenance reports.",
          "exact_text": "The Service Provider shall deliver source code, deployment scripts, user documentation, and monthly maintenance reports.",
          "page": 1,
          "id": "seg_005",
          "source": "data\\input\\1.pdf",
          "validation_status": "passed",
          "confidence": 0.99
        }
      ]
    },
    {
      "representative_keyword": "Payment Terms",
      "related_keywords": [
        "monthly service fee",
        "USD 4,500",
        "invoice",
        "Payment",
        "Late payments",
        "service suspension notice"
      ],
      "provision_type": "payment",
      "metadata": {
        "page": 1,
        "id": "seg_006",
        "source": "data\\input\\1.pdf",
        "clause_no": "5"
      },
      "evidences": [
        {
          "evidence_text": "The Client shall pay the Service Provider a monthly service fee of USD 4,500.",
          "exact_text": "The Client shall pay the Service Provider a monthly service fee of USD 4,500.",
          "page": 1,
          "id": "seg_006",
          "source": "data\\input\\1.pdf",
          "validation_status": "passed",
          "confidence": 0.99
        }
      ]
    },
    {
      "representative_keyword": "Automatic Renewal",
      "related_keywords": [
        "automatically renew",
        "one-year terms",
        "notice of non-renewal",
        "thirty (30) days"
      ],
      "provision_type": "renewal",
      "metadata": {
        "page": 1,
        "id": "seg_007",
        "source": "data\\input\\1.pdf",
        "clause_no": "6"
      },
      "evidences": [
        {
          "evidence_text": "This Agreement shall automatically renew for successive one-year terms unless either party gives written notice of non-renewal at least thirty (30) days before the end of the current term.",
          "exact_text": "This Agreement shall automatically renew for successive one-year terms unless either party gives written notice of non-renewal at least thirty (30) days before the end of the current term.",
          "page": 1,
          "id": "seg_007",
          "source": "data\\input\\1.pdf",
          "validation_status": "passed",
          "confidence": 0.99
        }
      ]
    },
    {
      "representative_keyword": "Termination",
      "related_keywords": [
        "terminate",
        "written notice",
        "thirty (30) days",
        "materially breaches",
        "cure the breach",
        "ten (10) business days"
      ],
      "provision_type": "termination",
      "metadata": {
        "page": 2,
        "id": "seg_008",
        "source": "data\\input\\1.pdf",
        "clause_no": "7"
      },
      "evidences": [
        {
          "evidence_text": "Either party may terminate this Agreement by giving thirty (30) days written notice to the other party.",
          "exact_text": "Either party may terminate this Agreement by giving thirty (30) days written notice to the other party.",
          "page": 2,
          "id": "seg_008",
          "source": "data\\input\\1.pdf",
          "validation_status": "passed",
          "confidence": 0.99
        }
      ]
    },
    {
      "representative_keyword": "Confidentiality",
      "related_keywords": [
        "confidential",
        "non-public business",
        "technical",
        "financial",
        "security",
        "customer information",
        "Confidential information",
        "disclosed"
      ],
      "provision_type": "confidentiality",
      "metadata": {
        "page": 2,
        "id": "seg_009",
        "source": "data\\input\\1.pdf",
        "clause_no": "8"
      },
      "evidences": [
        {
          "evidence_text": "Each party shall keep confidential all non-public business, technical, financial, security, and customer information received from the other party.",
          "exact_text": "Each party shall keep confidential all non-public business, technical, financial, security, and customer information received from the other party.",
          "page": 2,
          "id": "seg_009",
          "source": "data\\input\\1.pdf",
          "validation_status": "passed",
          "confidence": 0.99
        }
      ]
    },
    {
      "representative_keyword": "Data Security Obligations",
      "related_keywords": [
        "safeguards",
        "protect Client data",
        "production systems",
        "authorized personnel",
        "Security incidents",
        "forty-eight (48) hours"
      ],
      "provision_type": "obligations",
      "metadata": {
        "page": 2,
        "id": "seg_010",
        "source": "data\\input\\1.pdf",
        "clause_no": "9"
      },
      "evidences": [
        {
          "evidence_text": "The Service Provider shall use reasonable administrative, technical, and organizational safeguards to protect Client data.",
          "exact_text": "The Service Provider shall use reasonable administrative, technical, and organizational safeguards to protect Client data.",
          "page": 2,
          "id": "seg_010",
          "source": "data\\input\\1.pdf",
          "validation_status": "passed",
          "confidence": 0.99
        }
      ]
    },
    {
      "representative_keyword": "Limitation of Liability",
      "related_keywords": [
        "total liability",
        "service fees paid"
      ],
      "provision_type": "liability",
      "metadata": {
        "page": 2,
        "id": "seg_011",
        "source": "data\\input\\1.pdf",
        "clause_no": "10"
      },
      "evidences": [
        {
          "evidence_text": "The Service Provider total liability under this Agreement shall not exceed the total service fees paid by the Client during the three (3) months before the claim arose.",
          "exact_text": "The Service Provider total liability under this Agreement shall not exceed the total service fees paid by the Client during the three",
          "page": 2,
          "id": "seg_011",
          "source": "data\\input\\1.pdf",
          "validation_status": "passed",
          "confidence": 0.98
        }
      ]
    },
    {
      "representative_keyword": "Exclusion of Consequential Damages",
      "related_keywords": [
        "liable",
        "indirect, incidental, special, punitive, or consequential damages",
        "loss of profits",
        "business interruption"
      ],
      "provision_type": "liability",
      "metadata": {
        "page": 2,
        "id": "seg_012",
        "source": "data\\input\\1.pdf",
        "parent_section_title": "10. Liability"
      },
      "evidences": [
        {
          "evidence_text": "Neither party shall be liable for indirect, incidental, special, punitive, or consequential damages, including loss of profits or business interruption.",
          "exact_text": "Neither party shall be liable for indirect, incidental, special, punitive, or consequential damages, including loss of profits or business interruption.",
          "page": 2,
          "id": "seg_012",
          "source": "data\\input\\1.pdf",
          "validation_status": "passed",
          "confidence": 0.99
        }
      ]
    },
    {
      "representative_keyword": "Governing Law",
      "related_keywords": [
        "governed by",
        "laws of Vietnam"
      ],
      "provision_type": "governing_law",
      "metadata": {
        "page": 2,
        "id": "seg_013",
        "source": "data\\input\\1.pdf",
        "clause_no": "11"
      },
      "evidences": [
        {
          "evidence_text": "This Agreement shall be governed by and interpreted in accordance with the laws of Vietnam.",
          "exact_text": "This Agreement shall be governed by and interpreted in accordance with the laws of Vietnam.",
          "page": 2,
          "id": "seg_013",
          "source": "data\\input\\1.pdf",
          "validation_status": "passed",
          "confidence": 0.99
        }
      ]
    },
    {
      "representative_keyword": "Dispute Resolution",
      "related_keywords": [
        "dispute",
        "good-faith negotiation",
        "competent court",
        "Ho Chi Minh City, Vietnam"
      ],
      "provision_type": "dispute_resolution",
      "metadata": {
        "page": 2,
        "id": "seg_013",
        "source": "data\\input\\1.pdf",
        "clause_no": "11"
      },
      "evidences": [
        {
          "evidence_text": "Any dispute arising from this Agreement shall first be resolved through good-faith negotiation between the parties.",
          "exact_text": "Any dispute arising from this Agreement shall first be resolved through good-faith negotiation between the parties.",
          "page": 2,
          "id": "seg_013",
          "source": "data\\input\\1.pdf",
          "validation_status": "passed",
          "confidence": 0.98
        }
      ]
    },
    {
      "representative_keyword": "Notices",
      "related_keywords": [
        "notices",
        "in writing",
        "email",
        "registered mail",
        "deemed received"
      ],
      "provision_type": "notices",
      "metadata": {
        "page": 2,
        "id": "seg_014",
        "source": "data\\input\\1.pdf",
        "clause_no": "12"
      },
      "evidences": [
        {
          "evidence_text": "All notices under this Agreement must be in writing and sent by email or registered mail to the contact address provided by each party.",
          "exact_text": "All notices under this Agreement must be in writing and sent by email or registered mail to the contact address provided by each party.",
          "page": 2,
          "id": "seg_014",
          "source": "data\\input\\1.pdf",
          "validation_status": "passed",
          "confidence": 0.99
        }
      ]
    },
    {
      "representative_keyword": "Electronic Signatures",
      "related_keywords": [
        "sign this Agreement electronically",
        "Signature blocks"
      ],
      "provision_type": "signatures",
      "metadata": {
        "page": 2,
        "id": "seg_014",
        "source": "data\\input\\1.pdf",
        "clause_no": "12"
      },
      "evidences": [
        {
          "evidence_text": "Authorized representatives may sign this Agreement electronically.",
          "exact_text": "Authorized representatives may sign this Agreement electronically.",
          "page": 2,
          "id": "seg_014",
          "source": "data\\input\\1.pdf",
          "validation_status": "passed",
          "confidence": 0.99
        }
      ]
    }
  ]
}